zuspec/__build_num__.py
zuspec/__init__.py
zuspec/__main__.py
zuspec/arl_spec_loader.py
zuspec/loader.py
zuspec/my_class.py
zuspec/zuspec.py
zuspec/cmd/__init__.py
zuspec/cmd/cmd_parse_base.py
zuspec/cmd/cmd_registry.py
zuspec/cocotb/__init__.py
zuspec/gen/__init__.py
zuspec/gen/output.py
zuspec/impl/__init__.py
zuspec/impl/ctxt.py
zuspec/impl/generator_dot.py
zuspec/impl/seq_eval_iterator_processor.py
zuspec_cli-0.0.1.8428737035.dist-info/LICENSE
zuspec_cli-0.0.1.8428737035.dist-info/METADATA
zuspec_cli-0.0.1.8428737035.dist-info/WHEEL
zuspec_cli-0.0.1.8428737035.dist-info/entry_points.txt
zuspec_cli-0.0.1.8428737035.dist-info/top_level.txt
zuspec_cli-0.0.1.8428737035.dist-info/RECORD
